LICENSE.txt
MANIFEST.in
README.md
VERSION
requirements.txt
setup.py
src/pywgrib.c
src/pywgrib2.c
src/wgrib.c
src/grib2/Developement.doc
src/grib2/INSTALLING
src/grib2/README
src/grib2/README.EUMETSAT
src/grib2/README.Mac
src/grib2/README.clang
src/grib2/README.g2clib
src/grib2/README.gcc
src/grib2/README.gctpc
src/grib2/README.geolocation_plans
src/grib2/README.icc
src/grib2/README.ipolates
src/grib2/README.mysql
src/grib2/README.ncep
src/grib2/README.netcdf3
src/grib2/README.netcdf4
src/grib2/README.open64
src/grib2/README.openmp
src/grib2/README.pgi
src/grib2/formats.doc
src/grib2/gctpc20a.tgz
src/grib2/intro_grib2.doc
src/grib2/intro_grids.doc
src/grib2/jasper-1.900.1-14ubuntu3.2.debian.tgz
src/grib2/libaec-1.0.2.tar.gz
src/grib2/libpng-1.2.57.tar.gz
src/grib2/makefile
src/grib2/makefile.gctpc
src/grib2/makefile_hwrf
src/grib2/netcdf-3.6.3.tar.gz
src/grib2/proj-4.8.0.tar.gz
src/grib2/proj.h
src/grib2/somfor.c
src/grib2/sominv.c
src/grib2/tar_all
src/grib2/zlib-1.2.11.tar.gz
src/grib2/aux_progs/README
src/grib2/aux_progs/gmerge.c
src/grib2/aux_progs/gmerge.make
src/grib2/aux_progs/gmerge_13.c
src/grib2/aux_progs/grb2.h
src/grib2/aux_progs/grib_split.c
src/grib2/aux_progs/grib_split.make
src/grib2/aux_progs/gribtab2gribtable.c
src/grib2/aux_progs/rd_grib2_msg.c
src/grib2/aux_progs/smallest_4.c
src/grib2/aux_progs/smallest_4.make
src/grib2/aux_progs/smallest_grib2.c
src/grib2/aux_progs/smallest_grib2.make
src/grib2/aux_progs/uint8.c
src/grib2/ftn_api/Changes
src/grib2/ftn_api/README.txt
src/grib2/ftn_api/fort_wgrib2.c
src/grib2/ftn_api/makefile
src/grib2/ftn_api/wgrib2api.f90
src/grib2/ftn_api/wgrib2lowapi.f90
src/grib2/g2clib-1.4.0/cmplxpack.c
src/grib2/g2clib-1.4.0/compack.c
src/grib2/g2clib-1.4.0/comunpack.c
src/grib2/g2clib-1.4.0/dec_jpeg2000.c
src/grib2/g2clib-1.4.0/dec_png.c
src/grib2/g2clib-1.4.0/drstemplates.c
src/grib2/g2clib-1.4.0/drstemplates.h
src/grib2/g2clib-1.4.0/enc_jpeg2000.c
src/grib2/g2clib-1.4.0/enc_png.c
src/grib2/g2clib-1.4.0/g2_addfield.c
wgrib_python.egg-info/PKG-INFO
wgrib_python.egg-info/SOURCES.txt
wgrib_python.egg-info/dependency_links.txt
wgrib_python.egg-info/entry_points.txt
wgrib_python.egg-info/requires.txt
wgrib_python.egg-info/top_level.txt