Metadata-Version: 1.1
Name: wgrib-python
Version: 0.0.1.dev2
Summary: Simple python wgrib wrapper
Home-page: https://github.com/Lightslayer/wgrib-python
Author: Liam Deacon
Author-email: liam.m.deacon@gmail.com
License: MIT License
